spatialfeatureexperiment/__init__.py
spatialfeatureexperiment/aligned_spatialimage.py
spatialfeatureexperiment/coercions.py
spatialfeatureexperiment/sfe.py
spatialfeatureexperiment-0.0.5.dist-info/licenses/LICENSE.txt
spatialfeatureexperiment-0.0.5.dist-info/METADATA
spatialfeatureexperiment-0.0.5.dist-info/WHEEL
spatialfeatureexperiment-0.0.5.dist-info/top_level.txt
spatialfeatureexperiment-0.0.5.dist-info/RECORD
