Metadata-Version: 2.4
Name: SpatialFeatureExperiment
Version: 0.0.5
Summary: Container class for storing data from spatial feature experiments
Home-page: https://github.com/biocpy/spatialfeatureexperiment
Author: Jayaram Kancherla
Author-email: jayaram.kancherla@gmail.com
License: MIT
Project-URL: Documentation, https://github.com/biocpy/spatialfeatureexperiment
Platform: any
Classifier: Development Status :: 4 - Beta
Classifier: Programming Language :: Python
Requires-Python: >=3.9
License-File: LICENSE.txt
Requires-Dist: importlib-metadata; python_version < "3.8"
Requires-Dist: spatialexperiment>=0.0.12
Requires-Dist: pillow
Requires-Dist: geopandas
Requires-Dist: shapely
Requires-Dist: requests
Requires-Dist: rasterio
Requires-Dist: aicsimageio
Requires-Dist: numcodecs<=0.15.1
Requires-Dist: libpysal
Provides-Extra: optional
Requires-Dist: pandas; extra == "optional"
Requires-Dist: anndata; extra == "optional"
Requires-Dist: delayedarray; extra == "optional"
Provides-Extra: testing
Requires-Dist: setuptools; extra == "testing"
Requires-Dist: pytest; extra == "testing"
Requires-Dist: pytest-cov; extra == "testing"
Requires-Dist: pandas; extra == "testing"
Requires-Dist: anndata; extra == "testing"
Requires-Dist: delayedarray; extra == "testing"
Dynamic: license-file
